[
null,
{"id":1,"expanded":true,"name":"随机空间","order":8,"parentId":46,"scrollX":478.6666666666667,"scrollY":518.6666666666666},
{"id":2,"expanded":true,"name":"英雄召唤","order":2,"parentId":46,"scrollX":489.3333333333333,"scrollY":417.3333333333333},
{"id":3,"expanded":true,"name":"初见挑战","order":4,"parentId":46,"scrollX":658.2222222222222,"scrollY":640.4444444444445},
{"id":4,"expanded":true,"name":"转移空间","order":3,"parentId":46,"scrollX":658.2222222222222,"scrollY":559.5555555555555},
{"id":5,"expanded":true,"name":"终极空间","order":7,"parentId":46,"scrollX":658.2222222222222,"scrollY":587.1111111111111},
{"id":6,"expanded":false,"name":"飞云殿","order":9,"parentId":46,"scrollX":1037.7777777777778,"scrollY":1322.2222222222222},
{"id":7,"expanded":false,"name":"苍月挑战","order":5,"parentId":3,"scrollX":658.2222222222222,"scrollY":640.4444444444445},
{"id":8,"expanded":false,"name":"克里夫挑战","order":6,"parentId":3,"scrollX":491.1111111111111,"scrollY":504.44444444444446},
null,
null,
null,
null,
null,
null,
null,
null,
null,
null,
null,
null,
null,
null,
null,
null,
null,
null,
null,
null,
null,
null,
null,
null,
null,
null,
null,
null,
null,
null,
null,
null,
null,
null,
null,
null,
null,
{"id":46,"expanded":true,"name":"星图","order":1,"parentId":0,"scrollX":554.2222222222222,"scrollY":579.1111111111111}
]